[{"slno":"1","questionName":"Queue at the School","questionLink":"http://codeforces.com/problemset/problem/266/B","contestName":"Codeforces Round #163 (Div. 2)","difficultyLevel":"1"},{"slno":"2","questionName":"Xenia and Ringroad","questionLink":"http://codeforces.com/problemset/problem/339/B","contestName":"Codeforces Round #197 (Div. 2)","difficultyLevel":"2"},{"slno":"3","questionName":"Fedor and New Game","questionLink":"http://codeforces.com/problemset/problem/467/B","contestName":"Codeforces Round #267 (Div. 2)","difficultyLevel":"3"},{"slno":"4","questionName":"Random Teams","questionLink":"http://codeforces.com/problemset/problem/478/B","contestName":"Codeforces Round #273 (Div. 2)","difficultyLevel":"3"},{"slno":"5","questionName":"Vanya and Lanterns","questionLink":"http://codeforces.com/problemset/problem/492/B","contestName":"Codeforces Round #280 (Div. 2)","difficultyLevel":"3"},{"slno":"6","questionName":"Sort the Array","questionLink":"http://codeforces.com/problemset/problem/451/B","contestName":"Codeforces Round #258 (Div. 2)","difficultyLevel":"4"},{"slno":"7","questionName":"Lecture","questionLink":"http://codeforces.com/problemset/problem/499/B","contestName":"Codeforces Round #284 (Div. 2)","difficultyLevel":"2"},{"slno":"8","questionName":"T-primes","questionLink":"http://codeforces.com/problemset/problem/230/B","contestName":"Codeforces Round #142 (Div. 2)","difficultyLevel":"3"},{"slno":"9","questionName":"Anton and currency you all know","questionLink":"http://codeforces.com/problemset/problem/508/B","contestName":"Codeforces Round #288 (Div. 2)","difficultyLevel":"3"},{"slno":"10","questionName":"DZY Loves Strings","questionLink":"http://codeforces.com/problemset/problem/447/B","contestName":"Codeforces Round #255 (Div. 2)","difficultyLevel":"2"},{"slno":"11","questionName":"Amr and Pins","questionLink":"http://codeforces.com/problemset/problem/507/B","contestName":"Codeforces Round #287 (Div. 2)","difficultyLevel":"4"},{"slno":"12","questionName":"Little Pony and Sort by Shift","questionLink":"http://codeforces.com/problemset/problem/454/B","contestName":"Codeforces Round #259 (Div. 2)","difficultyLevel":"4"},{"slno":"13","questionName":"Jzzhu and Sequences","questionLink":"http://codeforces.com/problemset/problem/450/B","contestName":"Codeforces Round #257 (Div. 2)","difficultyLevel":"4"},{"slno":"14","questionName":"Roadside Trees (Simplified Edition)","questionLink":"http://codeforces.com/problemset/problem/265/B","contestName":"Codeforces Round #162 (Div. 2)","difficultyLevel":"2"},{"slno":"15","questionName":"Find Marble","questionLink":"http://codeforces.com/problemset/problem/285/B","contestName":"Codeforces Round #175 (Div. 2)","difficultyLevel":"3"},{"slno":"16","questionName":"Suffix Structures","questionLink":"http://codeforces.com/problemset/problem/448/B","contestName":"Codeforces Round #256 (Div. 2)","difficultyLevel":"4"},{"slno":"17","questionName":"Little Elephant and Magic Square","questionLink":"http://codeforces.com/problemset/problem/259/B","contestName":"Codeforces Round #157 (Div. 2)","difficultyLevel":"2"},{"slno":"18","questionName":"OR in Matrix","questionLink":"http://codeforces.com/problemset/problem/486/B","contestName":"Codeforces Round #277 (Div. 2)","difficultyLevel":"4"},{"slno":"19","questionName":"Football Kit","questionLink":"http://codeforces.com/problemset/problem/432/B","contestName":"Codeforces Round #246 (Div. 2)","difficultyLevel":"3"},{"slno":"20","questionName":"Little Girl and Game","questionLink":"http://codeforces.com/problemset/problem/276/B","contestName":"Codeforces Round #169 (Div. 2)","difficultyLevel":"3"},{"slno":"21","questionName":"Petya and Staircases","questionLink":"http://codeforces.com/problemset/problem/362/B","contestName":"Codeforces Round #212 (Div. 2)","difficultyLevel":"3"},{"slno":"22","questionName":"Books","questionLink":"http://codeforces.com/problemset/problem/279/B","contestName":"Codeforces Round #171 (Div. 2)","difficultyLevel":"4"},{"slno":"23","questionName":"Chat Online","questionLink":"http://codeforces.com/problemset/problem/469/B","contestName":"Codeforces Round #268 (Div. 2)","difficultyLevel":"3"},{"slno":"24","questionName":"Painting Pebbles","questionLink":"http://codeforces.com/problemset/problem/509/B","contestName":"Codeforces Round #289 (Div. 2, ACM ICPC Rules)","difficultyLevel":"2"},{"slno":"25","questionName":"Vasya and Wrestling","questionLink":"http://codeforces.com/problemset/problem/493/B","contestName":"Codeforces Round #281 (Div. 2)","difficultyLevel":"4"},{"slno":"26","questionName":"George and Round","questionLink":"http://codeforces.com/problemset/problem/387/B","contestName":"Codeforces Round #227 (Div. 2)","difficultyLevel":"3"},{"slno":"27","questionName":"The Fibonacci Segment","questionLink":"http://codeforces.com/problemset/problem/365/B","contestName":"Codeforces Round #213 (Div. 2)","difficultyLevel":"3"},{"slno":"28","questionName":"Trace","questionLink":"http://codeforces.com/problemset/problem/157/B","contestName":"Codeforces Round #110 (Div. 2)","difficultyLevel":"2"},{"slno":"29","questionName":"Sale","questionLink":"http://codeforces.com/problemset/problem/34/B","contestName":"Codeforces Beta Round #34 (Div. 2)","difficultyLevel":"2"},{"slno":"30","questionName":"Road Construction","questionLink":"http://codeforces.com/problemset/problem/330/B","contestName":"Codeforces Round #192 (Div. 2)","difficultyLevel":"3"},{"slno":"31","questionName":"Little Pigs and Wolves","questionLink":"http://codeforces.com/problemset/problem/116/B","contestName":"Codeforces Beta Round #87 (Div. 2 Only)","difficultyLevel":"3"},{"slno":"32","questionName":"Before an Exam","questionLink":"http://codeforces.com/problemset/problem/4/B","contestName":"Codeforces Beta Round #4 (Div. 2 Only)","difficultyLevel":"1"},{"slno":"33","questionName":"Painting Eggs","questionLink":"http://codeforces.com/problemset/problem/282/B","contestName":"Codeforces Round #173 (Div. 2)","difficultyLevel":"4"},{"slno":"34","questionName":"Lucky Substring","questionLink":"http://codeforces.com/problemset/problem/122/B","contestName":"Codeforces Beta Round #91 (Div. 2 Only)","difficultyLevel":"2"},{"slno":"35","questionName":"Combination","questionLink":"http://codeforces.com/problemset/problem/155/B","contestName":"Codeforces Round #109 (Div. 2)","difficultyLevel":"3"},{"slno":"36","questionName":"Jeff and Periods","questionLink":"http://codeforces.com/problemset/problem/352/B","contestName":"Codeforces Round #204 (Div. 2)","difficultyLevel":"3"},{"slno":"37","questionName":"Unary","questionLink":"http://codeforces.com/problemset/problem/133/B","contestName":"Codeforces Beta Round #96 (Div. 2)","difficultyLevel":"3"},{"slno":"38","questionName":"Polo the Penguin and Matrix","questionLink":"http://codeforces.com/problemset/problem/289/B","contestName":"Codeforces Round #177 (Div. 2)","difficultyLevel":"4"},{"slno":"39","questionName":"Dima and To-do List","questionLink":"http://codeforces.com/problemset/problem/366/B","contestName":"Codeforces Round #214 (Div. 2)","difficultyLevel":"3"},{"slno":"40","questionName":"Coins","questionLink":"http://codeforces.com/problemset/problem/58/B","contestName":"Codeforces Beta Round #54 (Div. 2)","difficultyLevel":"3"},{"slno":"41","questionName":"Han Solo and Lazer Gun","questionLink":"http://codeforces.com/problemset/problem/514/B","contestName":"Codeforces Round #291 (Div. 2)","difficultyLevel":"4"},{"slno":"42","questionName":"Garland","questionLink":"http://codeforces.com/problemset/problem/408/B","contestName":"Codeforces Round #239 (Div. 2)","difficultyLevel":"3"},{"slno":"43","questionName":"Flag Day","questionLink":"http://codeforces.com/problemset/problem/357/B","contestName":"Codeforces Round #207 (Div. 2)","difficultyLevel":"4"},{"slno":"44","questionName":"Art Union","questionLink":"http://codeforces.com/problemset/problem/416/B","contestName":"Codeforces Round #241 (Div. 2)","difficultyLevel":"3"},{"slno":"45","questionName":"Lucky String","questionLink":"http://codeforces.com/problemset/problem/110/B","contestName":"Codeforces Beta Round #84 (Div. 2 Only)","difficultyLevel":"2"},{"slno":"46","questionName":"Petya and Countryside","questionLink":"http://codeforces.com/problemset/problem/66/B","contestName":"Codeforces Beta Round #61 (Div. 2)","difficultyLevel":"2"},{"slno":"47","questionName":"Archer","questionLink":"http://codeforces.com/problemset/problem/312/B","contestName":"Codeforces Round #185 (Div. 2)","difficultyLevel":"3"},{"slno":"48","questionName":"Routine Problem","questionLink":"http://codeforces.com/problemset/problem/337/B","contestName":"Codeforces Round #196 (Div. 2)","difficultyLevel":"4"},{"slno":"49","questionName":"Color the Fence","questionLink":"http://codeforces.com/problemset/problem/349/B","contestName":"Codeforces Round #202 (Div. 2)","difficultyLevel":"4"},{"slno":"50","questionName":"Levko and Permutation","questionLink":"http://codeforces.com/problemset/problem/361/B","contestName":"Codeforces Round #210 (Div. 2)","difficultyLevel":"3"},{"slno":"51","questionName":"Vasya's Calendar","questionLink":"http://codeforces.com/problemset/problem/182/B","contestName":"Codeforces Round #117 (Div. 2)","difficultyLevel":"1"},{"slno":"52","questionName":"Reading","questionLink":"http://codeforces.com/problemset/problem/234/B","contestName":"Codeforces Round #145 (Div. 2, ACM-ICPC Rules)","difficultyLevel":"3"},{"slno":"53","questionName":"Phone Numbers","questionLink":"http://codeforces.com/problemset/problem/151/B","contestName":"Codeforces Round #107 (Div. 2)","difficultyLevel":"3"},{"slno":"54","questionName":"Permutation","questionLink":"http://codeforces.com/problemset/problem/359/B","contestName":"Codeforces Round #209 (Div. 2)","difficultyLevel":"3"},{"slno":"55","questionName":"Students and Shoelaces","questionLink":"http://codeforces.com/problemset/problem/129/B","contestName":"Codeforces Beta Round #94 (Div. 2 Only)","difficultyLevel":"3"},{"slno":"56","questionName":"Help Kingdom of Far Far Away 2","questionLink":"http://codeforces.com/problemset/problem/143/B","contestName":"Codeforces Round #102 (Div. 2)","difficultyLevel":"3"},{"slno":"57","questionName":"The Child and Set","questionLink":"http://codeforces.com/problemset/problem/437/B","contestName":"Codeforces Round #250 (Div. 2)","difficultyLevel":"4"},{"slno":"58","questionName":"Non-square Equation","questionLink":"http://codeforces.com/problemset/problem/233/B","contestName":"Codeforces Round #144 (Div. 2)","difficultyLevel":"4"},{"slno":"59","questionName":"Special Offer! Super Price 999 Bourles!","questionLink":"http://codeforces.com/problemset/problem/219/B","contestName":"Codeforces Round #135 (Div. 2)","difficultyLevel":"4"},{"slno":"60","questionName":"Little Elephant and Sorting","questionLink":"http://codeforces.com/problemset/problem/205/B","contestName":"Codeforces Round #129 (Div. 2)","difficultyLevel":"4"},{"slno":"61","questionName":"Walking in the Rain","questionLink":"http://codeforces.com/problemset/problem/192/B","contestName":"Codeforces Round #121 (Div. 2)","difficultyLevel":"3"},{"slno":"62","questionName":"Two Tables","questionLink":"http://codeforces.com/problemset/problem/228/B","contestName":"Codeforces Round #141 (Div. 2)","difficultyLevel":"4"},{"slno":"63","questionName":"Xenia and Spies","questionLink":"http://codeforces.com/problemset/problem/342/B","contestName":"Codeforces Round #199 (Div. 2)","difficultyLevel":"4"},{"slno":"64","questionName":"Lucky Numbers (easy)","questionLink":"http://codeforces.com/problemset/problem/96/B","contestName":"Codeforces Beta Round #77 (Div. 2 Only)","difficultyLevel":"4"},{"slno":"65","questionName":"Ping-Pong (Easy Version)","questionLink":"http://codeforces.com/problemset/problem/320/B","contestName":"Codeforces Round #189 (Div. 2)","difficultyLevel":"4"},{"slno":"66","questionName":"After Training","questionLink":"http://codeforces.com/problemset/problem/195/B","contestName":"Codeforces Round #123 (Div. 2)","difficultyLevel":"3"},{"slno":"67","questionName":"Magic, Wizardry and Wonders","questionLink":"http://codeforces.com/problemset/problem/231/B","contestName":"Codeforces Round #143 (Div. 2)","difficultyLevel":"4"},{"slno":"68","questionName":"Limit","questionLink":"http://codeforces.com/problemset/problem/197/B","contestName":"Codeforces Round #124 (Div. 2)","difficultyLevel":"4"},{"slno":"69","questionName":"Ancient Prophesy","questionLink":"http://codeforces.com/problemset/problem/260/B","contestName":"Codeforces Round #158 (Div. 2)","difficultyLevel":"4"},{"slno":"70","questionName":"Hometask","questionLink":"http://codeforces.com/problemset/problem/214/B","contestName":"Codeforces Round #131 (Div. 2)","difficultyLevel":"4"},{"slno":"71","questionName":"Well-known Numbers","questionLink":"http://codeforces.com/problemset/problem/225/B","contestName":"Codeforces Round #139 (Div. 2)","difficultyLevel":"4"},{"slno":"72","questionName":"Settlers' Training","questionLink":"http://codeforces.com/problemset/problem/63/B","contestName":"Codeforces Beta Round #59 (Div. 2)","difficultyLevel":"3"},{"slno":"73","questionName":"Nearest Fraction","questionLink":"http://codeforces.com/problemset/problem/281/B","contestName":"Codeforces Round #172 (Div. 2)","difficultyLevel":"4"},{"slno":"74","questionName":"Counting Rhombi","questionLink":"http://codeforces.com/problemset/problem/189/B","contestName":"Codeforces Round #119 (Div. 2)","difficultyLevel":"3"},{"slno":"75","questionName":"Friends","questionLink":"http://codeforces.com/problemset/problem/94/B","contestName":"Codeforces Beta Round #76 (Div. 2 Only)","difficultyLevel":"3"},{"slno":"76","questionName":"Undoubtedly Lucky Numbers","questionLink":"http://codeforces.com/problemset/problem/244/B","contestName":"Codeforces Round #150 (Div. 2)","difficultyLevel":"4"},{"slno":"77","questionName":"Forming Teams","questionLink":"http://codeforces.com/problemset/problem/216/B","contestName":"Codeforces Round #133 (Div. 2)","difficultyLevel":"4"},{"slno":"78","questionName":"Inna and Nine","questionLink":"http://codeforces.com/problemset/problem/374/B","contestName":"Codeforces Round #220 (Div. 2)","difficultyLevel":"4"},{"slno":"79","questionName":"Bets","questionLink":"http://codeforces.com/problemset/problem/69/B","contestName":"Codeforces Beta Round #63 (Div. 2)","difficultyLevel":"3"},{"slno":"80","questionName":"Young Photographer","questionLink":"http://codeforces.com/problemset/problem/14/B","contestName":"Codeforces Beta Round #14 (Div. 2)","difficultyLevel":"4"},{"slno":"81","questionName":"Martian Clock","questionLink":"http://codeforces.com/problemset/problem/149/B","contestName":"Codeforces Round #106 (Div. 2)","difficultyLevel":"4"},{"slno":"82","questionName":"Jury Size","questionLink":"http://codeforces.com/problemset/problem/254/B","contestName":"Codeforces Round #155 (Div. 2)","difficultyLevel":"4"},{"slno":"83","questionName":"Hard Work","questionLink":"http://codeforces.com/problemset/problem/61/B","contestName":"Codeforces Beta Round #57 (Div. 2)","difficultyLevel":"4"},{"slno":"84","questionName":"Testing Pants for Sadness","questionLink":"http://codeforces.com/problemset/problem/103/A","contestName":"Codeforces Beta Round #80 (Div. 1 Only) & Codeforces Beta Round #80 (Div. 2 Only)","difficultyLevel":"3"},{"slno":"85","questionName":"Running Student","questionLink":"http://codeforces.com/problemset/problem/9/B","contestName":"Codeforces Beta Round #9 (Div. 2 Only)","difficultyLevel":"4"},{"slno":"86","questionName":"Tournament","questionLink":"http://codeforces.com/problemset/problem/27/B","contestName":"Codeforces Beta Round #27 (Codeforces format, Div. 2)","difficultyLevel":"3"},{"slno":"87","questionName":"Magical Array","questionLink":"http://codeforces.com/problemset/problem/83/A","contestName":"Codeforces Beta Round #72 (Div. 1 Only) & Codeforces Beta Round #72 (Div. 2 Only)","difficultyLevel":"3"},{"slno":"88","questionName":"Help Chef Gerasim","questionLink":"http://codeforces.com/problemset/problem/99/B","contestName":"Codeforces Beta Round #78 (Div. 2 Only)","difficultyLevel":"4"},{"slno":"89","questionName":"Convex Shape","questionLink":"http://codeforces.com/problemset/problem/275/B","contestName":"Codeforces Round #168 (Div. 2)","difficultyLevel":"4"},{"slno":"90","questionName":"Surrounded","questionLink":"http://codeforces.com/problemset/problem/190/B","contestName":"Codeforces Round #120 (Div. 2)","difficultyLevel":"5"},{"slno":"91","questionName":"Spoilt Permutation","questionLink":"http://codeforces.com/problemset/problem/56/B","contestName":"Codeforces Beta Round #52 (Div. 2)","difficultyLevel":"4"},{"slno":"92","questionName":"PFAST Inc.","questionLink":"http://codeforces.com/problemset/problem/114/B","contestName":"Codeforces Beta Round #86 (Div. 2 Only)","difficultyLevel":"4"},{"slno":"93","questionName":"Martian Dollar","questionLink":"http://codeforces.com/problemset/problem/41/B","contestName":"Codeforces Beta Round #40 (Div. 2)","difficultyLevel":"4"},{"slno":"94","questionName":"Bargaining Table","questionLink":"http://codeforces.com/problemset/problem/22/B","contestName":"Codeforces Beta Round #22 (Div. 2 Only)","difficultyLevel":"5"},{"slno":"95","questionName":"Sysadmin Bob","questionLink":"http://codeforces.com/problemset/problem/31/B","contestName":"Codeforces Beta Round #31 (Div. 2, Codeforces format)","difficultyLevel":"4"},{"slno":"96","questionName":"Facetook Priority Wall","questionLink":"http://codeforces.com/problemset/problem/75/B","contestName":"Codeforces Beta Round #67 (Div. 2)","difficultyLevel":"4"},{"slno":"97","questionName":"Maximal Area Quadrilateral","questionLink":"http://codeforces.com/problemset/problem/340/B","contestName":"Codeforces Round #198 (Div. 2)","difficultyLevel":"4"},{"slno":"98","questionName":"Traffic Lights","questionLink":"http://codeforces.com/problemset/problem/29/B","contestName":"Codeforces Beta Round #29 (Div. 2, Codeforces format)","difficultyLevel":"4"},{"slno":"99","questionName":"Blog Photo","questionLink":"http://codeforces.com/problemset/problem/53/B","contestName":"Codeforces Beta Round #49 (Div. 2)","difficultyLevel":"5"},{"slno":"100","questionName":"Three matrices","questionLink":"http://codeforces.com/problemset/problem/393/B","contestName":"Codeforces Round #230 (Div. 2)","difficultyLevel":"7"}]